{
  "project_info": {
    "project_number": "1073407728319",
    "project_id": "android-learning-cb29c",
    "storage_bucket": "android-learning-cb29c.appspot.com"
  },
  "client": [
    {
      "client_info": {
        "mobilesdk_app_id": "1:1073407728319:android:9700e71ddbc833190ec40a",
        "android_client_info": {
          "package_name": "com.o5appstudio.androidconcepts"
        }
      },
      "oauth_client": [],
      "api_key": [
        {
          "current_key": "AIzaSyAu4jGQQog5G0IPI6aokJCYmNtMzxygcxY"
        }
      ],
      "services": {
        "appinvite_service": {
          "other_platform_oauth_client": []
        }
      }
    },
    {
      "client_info": {
        "mobilesdk_app_id": "1:1073407728319:android:7fdd8db550e5d7510ec40a",
        "android_client_info": {
          "package_name": "com.o5appstudio.androidlearning"
        }
      },
      "oauth_client": [],
      "api_key": [
        {
          "current_key": "AIzaSyAu4jGQQog5G0IPI6aokJCYmNtMzxygcxY"
        }
      ],
      "services": {
        "appinvite_service": {
          "other_platform_oauth_client": []
        }
      }
    }
  ],
  "configuration_version": "1"
}